{
 "category": "Domains",
 "charts": [
  {
   "chart_name": "Warehouse wise Stock Value",
   "label": "Warehouse wise Stock Value"
  }
 ],
 "creation": "2021-08-02 00:23:52.965814",
 "developer_mode_only": 0,
 "disable_user_customization": 0,
 "docstatus": 0,
 "doctype": "Workspace",
 "extends_another_page": 0,
 "hide_custom": 0,
 "icon": "assets",
 "idx": 0,
 "is_default": 0,
 "is_standard": 1,
 "label": "Ecommerce",
 "links": [
  {
   "hidden": 0,
   "is_query_report": 0,
   "label": "Settings",
   "link_type": "DocType",
   "onboard": 0,
   "type": "Card Break"
  },
  {
   "hidden": 0,
   "is_query_report": 0,
   "label": "App Settings",
   "link_to": "Roona App Setting",
   "link_type": "DocType",
   "onboard": 0,
   "type": "Link"
  },
  {
   "hidden": 0,
   "is_query_report": 0,
   "label": "Textlocal Setting",
   "link_to": "Textlocal Setting",
   "link_type": "DocType",
   "onboard": 0,
   "type": "Link"
  },
  {
   "hidden": 0,
   "is_query_report": 0,
   "label": "Whitelabel Setting",
   "link_to": "Whitelabel Setting",
   "link_type": "DocType",
   "onboard": 0,
   "type": "Link"
  },
  {
   "hidden": 0,
   "is_query_report": 0,
   "label": "Loyalty Program",
   "link_type": "DocType",
   "onboard": 0,
   "type": "Card Break"
  },
  {
   "hidden": 0,
   "is_query_report": 0,
   "label": "Loyalty Program",
   "link_to": "Loyalty Program",
   "link_type": "DocType",
   "onboard": 0,
   "type": "Link"
  },
  {
   "hidden": 0,
   "is_query_report": 0,
   "label": "Loyalty Point Entry",
   "link_to": "Loyalty Point Entry",
   "link_type": "DocType",
   "onboard": 0,
   "type": "Link"
  },
  {
   "hidden": 0,
   "is_query_report": 0,
   "label": "Masters",
   "link_type": "DocType",
   "onboard": 0,
   "type": "Card Break"
  },
  {
   "hidden": 0,
   "is_query_report": 0,
   "label": "Products",
   "link_to": "Item",
   "link_type": "DocType",
   "onboard": 0,
   "type": "Link"
  },
  {
   "hidden": 0,
   "is_query_report": 0,
   "label": "Product Category",
   "link_to": "Item Group",
   "link_type": "DocType",
   "onboard": 0,
   "type": "Link"
  },
  {
   "hidden": 0,
   "is_query_report": 0,
   "label": "Delivery Location",
   "link_to": "Delivery Location",
   "link_type": "DocType",
   "onboard": 0,
   "type": "Link"
  },
  {
   "hidden": 0,
   "is_query_report": 0,
   "label": "Delivery Slot",
   "link_to": "Delivery Slot",
   "link_type": "DocType",
   "onboard": 0,
   "type": "Link"
  },
  {
   "hidden": 0,
   "is_query_report": 0,
   "label": "Sales",
   "link_type": "DocType",
   "onboard": 0,
   "type": "Card Break"
  },
  {
   "hidden": 0,
   "is_query_report": 0,
   "label": "Sales Order",
   "link_to": "Sales Order",
   "link_type": "DocType",
   "onboard": 0,
   "type": "Link"
  },
  {
   "hidden": 0,
   "is_query_report": 0,
   "label": "Payment",
   "link_to": "Payment Entry",
   "link_type": "DocType",
   "onboard": 0,
   "type": "Link"
  },
  {
   "hidden": 0,
   "is_query_report": 0,
   "label": "Delivery Note",
   "link_to": "Delivery Note",
   "link_type": "DocType",
   "onboard": 0,
   "type": "Link"
  },
  {
   "hidden": 0,
   "is_query_report": 0,
   "label": "Packing Slip",
   "link_to": "Packing Slip",
   "link_type": "DocType",
   "onboard": 0,
   "type": "Link"
  },
  {
   "hidden": 0,
   "is_query_report": 0,
   "label": "Sales Invoice",
   "link_to": "Sales Invoice",
   "link_type": "DocType",
   "onboard": 0,
   "type": "Link"
  }
 ],
 "modified": "2021-08-02 16:18:18.712390",
 "modified_by": "Administrator",
 "module": "Roona",
 "name": "Ecommerce",
 "owner": "Administrator",
 "pin_to_bottom": 1,
 "pin_to_top": 0,
 "shortcuts": [
  {
   "doc_view": "List",
   "label": "Products",
   "link_to": "Item",
   "type": "DocType"
  },
  {
   "doc_view": "Tree",
   "label": "Product Category",
   "link_to": "Item Group",
   "type": "DocType"
  }
 ]
}